[{"place_id": 168818427, "licence": "Data \u00a9 OpenStreetMap contributors, ODbL 1.0. http://osm.org/copyright", "osm_type": "node", "osm_id": 5927615655, "lat": "51.0947123", "lon": "17.0148530", "class": "amenity", "type": "doctors", "place_rank": 30, "importance": 7.647592889291245e-05, "addresstype": "amenity", "name": "Medix", "display_name": "Medix, 16-17, Plac Ludwika Hirszfelda, Powsta\u0144c\u00f3w \u015al\u0105skich, Wroc\u0142aw, Lower Silesian Voivodeship, 53-413, Poland", "boundingbox": ["51.0946623", "51.0947623", "17.0148030", "17.0149030"]}]